smspy/__init__.py
smspy/core.py
smspy-0.5.0.dist-info/DESCRIPTION.rst
smspy-0.5.0.dist-info/METADATA
smspy-0.5.0.dist-info/RECORD
smspy-0.5.0.dist-info/WHEEL
smspy-0.5.0.dist-info/metadata.json
smspy-0.5.0.dist-info/top_level.txt
